MANIFEST.in
README
setup.py
cart/.models.py.swp
cart/.urls.py.swp
cart/.views.py.swp
cart/__init__.py
cart/manager.py
cart/models.py
cart/urls.py
cart/views.py
cart/templatetags/__init__.py
cart/templatetags/cart_tags.py
django_simple_cart.egg-info/PKG-INFO
django_simple_cart.egg-info/SOURCES.txt
django_simple_cart.egg-info/dependency_links.txt
django_simple_cart.egg-info/top_level.txt