Metadata-Version: 1.0
Name: django-simple-cart
Version: 0.1.0
Summary: Simple cart for django based shop
Home-page: http://bitbucket.org/lorien/django-simple-cart/
Author: Grigoriy Petukhov
Author-email: lorien@lorien.name
License: BSD
Keywords: django application development shop cart
Platform: UNKNOWN
Classifier: Development Status :: 4 - Beta
Classifier: Environment :: Web Environment
Classifier: Framework :: Django
Classifier: Intended Audience :: Developers
Classifier: License :: OSI Approved :: BSD License
Classifier: Operating System :: OS Independent
Classifier: Programming Language :: Python
Classifier: Topic :: Software Development :: Libraries :: Python Modules
